{
    "schemaVersion": 1,

    "id": "memory-check",
    "version": "${version}",

    "name": "Memory Check",
    "description": "Quickly check your server's memory usage!",

    "license": "GPL-3.0-only",
    "authors": [
        "Wojciech Paruch"
    ],

    "contact": {
        "homepage": "https://modrinth.com/mod/memory-check",
        "sources": "https://github.com/Blayung/memory-check",
        "issues": "https://github.com/Blayung/memory-check/issues",
        "email": "teamaster69@proton.me"
    },

    "environment": "server",
    "entrypoints": {
        "server": [
            "com.blay.memcheck.MemoryCheck"
        ]
    },

    "depends": {
        "fabric-api": "*"
    }
}
